pyp0f/__init__.py
pyp0f/exceptions.py
pyp0f/options.py
pyp0f/data/p0f.fp
pyp0f/database/__init__.py
pyp0f/database/database.py
pyp0f/database/records_database.py
pyp0f/database/labels/__init__.py
pyp0f/database/labels/base.py
pyp0f/database/labels/label.py
pyp0f/database/labels/mtu.py
pyp0f/database/parse/__init__.py
pyp0f/database/parse/parser.py
pyp0f/database/parse/utils.py
pyp0f/database/parse/wildcard.py
pyp0f/database/records/__init__.py
pyp0f/database/records/base.py
pyp0f/database/records/http.py
pyp0f/database/records/mtu.py
pyp0f/database/records/tcp.py
pyp0f/database/signatures/__init__.py
pyp0f/database/signatures/base.py
pyp0f/database/signatures/http.py
pyp0f/database/signatures/mtu.py
pyp0f/database/signatures/tcp.py
pyp0f/fingerprint/__init__.py
pyp0f/fingerprint/http.py
pyp0f/fingerprint/mtu.py
pyp0f/fingerprint/tcp.py
pyp0f/fingerprint/uptime.py
pyp0f/fingerprint/results/__init__.py
pyp0f/fingerprint/results/base.py
pyp0f/fingerprint/results/http.py
pyp0f/fingerprint/results/mtu.py
pyp0f/fingerprint/results/tcp.py
pyp0f/fingerprint/results/uptime.py
pyp0f/impersonate/__init__.py
pyp0f/impersonate/mtu.py
pyp0f/impersonate/tcp.py
pyp0f/impersonate/utils.py
pyp0f/net/__init__.py
pyp0f/net/packet.py
pyp0f/net/quirks.py
pyp0f/net/scapy.py
pyp0f/net/layers/__init__.py
pyp0f/net/layers/base.py
pyp0f/net/layers/ip.py
pyp0f/net/layers/http/__init__.py
pyp0f/net/layers/http/header.py
pyp0f/net/layers/http/http.py
pyp0f/net/layers/http/read.py
pyp0f/net/layers/tcp/__init__.py
pyp0f/net/layers/tcp/flags.py
pyp0f/net/layers/tcp/options.py
pyp0f/net/layers/tcp/tcp.py
pyp0f/net/signatures/__init__.py
pyp0f/net/signatures/base.py
pyp0f/net/signatures/http.py
pyp0f/net/signatures/mtu.py
pyp0f/net/signatures/tcp.py
pyp0f/utils/__init__.py
pyp0f/utils/path.py
pyp0f/utils/slots.py
pyp0f/utils/time.py
pyp0f-0.3.0.dist-info/LICENSE
pyp0f-0.3.0.dist-info/METADATA
pyp0f-0.3.0.dist-info/WHEEL
pyp0f-0.3.0.dist-info/top_level.txt
pyp0f-0.3.0.dist-info/RECORD
