Metadata-Version: 2.1
Name: pyp0f
Version: 0.3.0
Summary: p0f v3 with impersonation spoofing, written in Python
Author-email: Itay Margolin <itay62848@gmail.com>
License: MIT License
Project-URL: Homepage, https://github.com/Nisitay/pyp0f
Project-URL: Source, https://github.com/Nisitay/pyp0f
Project-URL: Documentation, https://github.com/Nisitay/pyp0f/blob/master/docs/README.md
Classifier: License :: OSI Approved :: MIT License
Classifier: Development Status :: 4 - Beta
Classifier: Environment :: Console
Classifier: Operating System :: OS Independent
Classifier: Programming Language :: Python
Classifier: Programming Language :: Python :: 3
Classifier: Programming Language :: Python :: 3 :: Only
Classifier: Programming Language :: Python :: 3.7
Classifier: Programming Language :: Python :: 3.8
Classifier: Programming Language :: Python :: 3.9
Classifier: Programming Language :: Python :: 3.10
Classifier: Programming Language :: Python :: Implementation :: CPython
Classifier: Topic :: Security
Classifier: Topic :: Internet
Classifier: Topic :: System :: Networking :: Monitoring
Classifier: Topic :: Software Development :: Libraries
Classifier: Topic :: Software Development :: Libraries :: Python Modules
Classifier: Typing :: Typed
Requires-Python: >=3.7
Provides-Extra: dev
License-File: LICENSE
